orco/__init__.py
orco/builder.py
orco/cfggen.py
orco/cli.py
orco/consts.py
orco/globals.py
orco/job.py
orco/jobfunctions.py
orco/jobsetup.py
orco/report.py
orco/runtime.py
orco/ext/__init__.py
orco/ext/pandas.py
orco/ext/pyplot.py
orco/internals/__init__.py
orco/internals/browser.py
orco/internals/context.py
orco/internals/database.py
orco/internals/executor.py
orco/internals/key.py
orco/internals/plan.py
orco/internals/runner.py
orco/internals/utils.py
orco/static/asset-manifest.json.gz
orco/static/index.html.gz
orco/static/manifest.json.gz
orco/static/precache-manifest.cc1bcbb9455bfa2c8f2b247af8622500.js.gz
orco/static/service-worker.js.gz
orco/static/css/2.861f4f67.chunk.css.gz
orco/static/css/2.861f4f67.chunk.css.map.gz
orco/static/css/main.418ea95c.chunk.css.gz
orco/static/css/main.418ea95c.chunk.css.map.gz
orco/static/js/2.3cd9276e.chunk.js.LICENSE.txt.gz
orco/static/js/2.3cd9276e.chunk.js.gz
orco/static/js/2.3cd9276e.chunk.js.map.gz
orco/static/js/main.ef71cb43.chunk.js.gz
orco/static/js/main.ef71cb43.chunk.js.map.gz
orco/static/js/runtime-main.f8c5b4be.js.gz
orco/static/js/runtime-main.f8c5b4be.js.map.gz
orco-0.6.1.dist-info/METADATA
orco-0.6.1.dist-info/RECORD
orco-0.6.1.dist-info/WHEEL
orco-0.6.1.dist-info/top_level.txt
