Metadata-Version: 2.1
Name: orco
Version: 0.6.1
Summary: Organized Computing
Home-page: http://github.com/spirali/orco
Author: Stanislav Bohm
Author-email: UNKNOWN
License: UNKNOWN
Platform: UNKNOWN
Classifier: Programming Language :: Python :: 3
Classifier: License :: OSI Approved :: MIT License
Classifier: Operating System :: OS Independent
Requires-Dist: sqlalchemy
Requires-Dist: cloudpickle
Requires-Dist: flask
Requires-Dist: flask-restful
Requires-Dist: flask-cors
Requires-Dist: pandas
Requires-Dist: tqdm
Requires-Dist: waitress
Requires-Dist: capturer
